{
    "key": "group_5baddc5cf3924",
    "title": "Shop Pages",
    "fields": [
        {
            "key": "field_5baddd5b01864",
            "label": "Title hero",
            "name": "sp-titlehero",
            "aria-label": "",
            "type": "text",
            "instructions": "",
            "required": 0,
            "conditional_logic": 0,
            "wrapper": {
                "width": "50",
                "class": "",
                "id": ""
            },
            "default_value": "",
            "placeholder": "",
            "prepend": "",
            "append": "",
            "maxlength": ""
        },
        {
            "key": "field_5baddd9801865",
            "label": "Title site",
            "name": "sp-titlesite",
            "aria-label": "",
            "type": "text",
            "instructions": "",
            "required": 0,
            "conditional_logic": 0,
            "wrapper": {
                "width": "50",
                "class": "",
                "id": ""
            },
            "default_value": "",
            "placeholder": "",
            "prepend": "",
            "append": "",
            "maxlength": ""
        },
        {
            "key": "field_5badef8447d40",
            "label": "Pre content",
            "name": "sp-precontent",
            "aria-label": "",
            "type": "wysiwyg",
            "instructions": "",
            "required": 0,
            "conditional_logic": 0,
            "wrapper": {
                "width": "100",
                "class": "",
                "id": ""
            },
            "default_value": "",
            "tabs": "all",
            "toolbar": "full",
            "media_upload": 1,
            "delay": 0
        },
        {
            "key": "field_5badddc8d8acb",
            "label": "Sub Title",
            "name": "sp-subtitle",
            "aria-label": "",
            "type": "text",
            "instructions": "",
            "required": 0,
            "conditional_logic": 0,
            "wrapper": {
                "width": "100",
                "class": "",
                "id": ""
            },
            "default_value": "",
            "placeholder": "",
            "prepend": "",
            "append": "",
            "maxlength": ""
        },
        {
            "key": "field_5badde9cd196a",
            "label": "Content",
            "name": "sp-content",
            "aria-label": "",
            "type": "wysiwyg",
            "instructions": "",
            "required": 0,
            "conditional_logic": 0,
            "wrapper": {
                "width": "100",
                "class": "",
                "id": ""
            },
            "default_value": "",
            "tabs": "all",
            "toolbar": "full",
            "media_upload": 1,
            "delay": 0
        }
    ],
    "location": [
        [
            {
                "param": "page",
                "operator": "==",
                "value": "419"
            }
        ],
        [
            {
                "param": "page",
                "operator": "==",
                "value": "439"
            }
        ]
    ],
    "menu_order": 0,
    "position": "normal",
    "style": "default",
    "label_placement": "top",
    "instruction_placement": "label",
    "hide_on_screen": [
        "the_content"
    ],
    "active": false,
    "description": "KF- shop pages",
    "show_in_rest": 0,
    "acfml_field_group_mode": "advanced",
    "modified": 1686070400
}